comparator/__init__.py
comparator/comparison.py
comparator/decision_problem.py
comparator/utils.py
comparator/evaluators/__init__.py
comparator/evaluators/abstract_evaluator.py
comparator/evaluators/topsis_evaluator.py
mcdacomparator-0.0.1.dist-info/LICENSE
mcdacomparator-0.0.1.dist-info/METADATA
mcdacomparator-0.0.1.dist-info/WHEEL
mcdacomparator-0.0.1.dist-info/top_level.txt
mcdacomparator-0.0.1.dist-info/RECORD
